deepctl_shared_utils/__init__.py
deepctl_shared_utils/models.py
deepctl_shared_utils/py.typed
deepctl_shared_utils/validation.py
deepctl_shared_utils-0.1.10.dist-info/METADATA
deepctl_shared_utils-0.1.10.dist-info/WHEEL
deepctl_shared_utils-0.1.10.dist-info/top_level.txt
deepctl_shared_utils-0.1.10.dist-info/RECORD
